Metadata-Version: 2.1
Name: midtermmattagut
Version: 0.0.1
Summary: Midterm package
Home-page: https://github.com/MattAGUT/midtermmattagut
Author: Matthew Gerloff
Author-email: mapache.tn@gmail.com
License: MIT license
Keywords: midtermmattagut
Classifier: Development Status :: 2 - Pre-Alpha
Classifier: Intended Audience :: Developers
Classifier: License :: OSI Approved :: MIT License
Classifier: Natural Language :: English
Classifier: Programming Language :: Python :: 3
Classifier: Programming Language :: Python :: 3.7
Classifier: Programming Language :: Python :: 3.8
Classifier: Programming Language :: Python :: 3.9
Classifier: Programming Language :: Python :: 3.10
Requires-Python: >=3.7
License-File: LICENSE
